mailpad/__init__.py
mailpad/mail.py
mailpad/mailAI.py
mailpad-1.0.2.dist-info/LICENSE
mailpad-1.0.2.dist-info/METADATA
mailpad-1.0.2.dist-info/WHEEL
mailpad-1.0.2.dist-info/top_level.txt
mailpad-1.0.2.dist-info/RECORD
