Metadata-Version: 2.1
Name: mailpad
Version: 1.0.2
Summary: Python Mailing Library
Home-page: https://mailpad.tech/
Author: Shivansh Dwivedi
Author-email: <me@shivanshdwivedi.tech>
License: MIT
Keywords: mailpad,python,mail,email,email client,smtp
Classifier: Development Status :: 4 - Beta
Classifier: Intended Audience :: Developers
Classifier: Intended Audience :: Science/Research
Classifier: Intended Audience :: Information Technology
Classifier: Programming Language :: Python
Classifier: Operating System :: OS Independent
License-File: LICENSE
Requires-Dist: langchain
